Ejercicio 3/ALU.v
module ALU (input wire [3:0] A,B, 
	    input wire [2:0] funcion, 
	    output logic[3:0] resul);

reg[3:0] Alu_resultado;
parameter f1 = 3'b000;
parameter f2 = 3'b001;
parameter f3 = 3'b010;
parameter f4 = 3'b011;
parameter f5 = 3'b100;
parameter f6 = 3'b101;
parameter f7 = 3'b110;
parameter f8 = 3'b111;

always@(*) begin
	case(funcion)
		f1: 
			Alu_resultado = A & B;
		f2: 
			Alu_resultado = A | B;
		f3: 
			Alu_resultado = A + B;
		f4: 
			Alu_resultado = 4'b0000;
		f5: 
			Alu_resultado = A & ~B;
		f6: 
			Alu_resultado = A | ~B;
		f7: 
			Alu_resultado = A - B;
		f8: 
			Alu_resultado = (A<B)? 4'd1:4'd0 ;

		default: Alu_resultado = A + B;
	endcase
	assign resul = Alu_resultado;
end
endmodule

Ejercicio 3/ALU_tb.v
module testbench();

reg [3:0] A,B;
reg [2:0] opcion;
wire [3:0] resultado;

ALU m1(A, B, opcion, resultado);

initial begin
	$display("  opcion | operacion    |");
	$display("-----------------------");
	$display("   000    |    A AND B   |");
	$display("   001    |    A  OR B   |");
	$display("   010    |    A   + B   |");
	$display("   011    |      NULO    |");
	$display("   100    |    A AND B'  |");
	$display("   101    |    A  OR B'  |");
	$display("   110    |    A   - B   |");
	$display("   111    |      STL     |");

	$display(" ");
	$display("  A    |  B   |opcion|  Y  |");
	$display("-----|------|------|-----|");
	$monitor("%b |  %b| %b  | %b|", A, B, opcion, resultado);

	   A = 4'b0101; B = 4'b1011; opcion = 3'b000;
	#1 A = 4'b0101; B = 4'b1011; opcion = 3'b001;
	#1 A = 4'b0101; B = 4'b1011; opcion = 3'b010;
	#1 A = 4'b1101; B = 4'b1001; opcion = 3'b011;
	#1 A = 4'b0001; B = 4'b1001; opcion = 3'b100;
	#1 A = 4'b1111; B = 4'b0001; opcion = 3'b101;
	#1 A = 4'b1101; B = 4'b1101; opcion = 3'b110;
	#1 A = 4'b1010; B = 4'b1111; opcion = 3'b111;
	#1 A = 4'b1000; B = 4'b1011; opcion = 3'b101;
	#1 A = 4'b1100; B = 4'b0011; opcion = 3'b010;
	#1 A = 4'b1010; B = 4'b0111; opcion = 3'b111;
	
	
end



initial
	#20 $finish;		
initial begin
	$dumpfile("ALU_tb.vcd");
	$dumpvars(0, testbench);
	end
endmodule

Ejercicio 3/ALU_tb.vcd
$date
	Fri Oct 23 19:29:25 2020
$end
$version
	Icarus Verilog
$end
$timescale
	1ps
$end
$scope module testbench $end
$var wire 4 ! resultado [3:0] $end
$var reg 4 " A [3:0] $end
$var reg 4 # B [3:0] $end
$var reg 3 $ opcion [2:0] $end
$scope module m1 $end
$var wire 4 % A [3:0] $end
$var wire 4 & B [3:0] $end
$var wire 3 ' funcion [2:0] $end
$var reg 4 ( Alu_resultado [3:0] $end
$var reg 4 ) resul [3:0] $end
$upscope $end
$upscope $end
$enddefinitions $end
#0
$dumpvars
b1 )
b1 (
b0 '
b1011 &
b101 %
b0 $
b1011 #
b101 "
b1 !
$end
#1
b1111 !
b1111 )
b1111 (
b1 $
b1 '
#2
b0 !
b0 )
b0 (
b10 $
b10 '
#3
b11 $
b11 '
b1001 #
b1001 &
b1101 "
b1101 %
#4
b100 $
b100 '
b1 "
b1 %
#5
b1111 !
b1111 )
b1111 (
b101 $
b101 '
b1 #
b1 &
b1111 "
b1111 %
#6
b0 !
b0 )
b0 (
b110 $
b110 '
b1101 #
b1101 &
b1101 "
b1101 %
#7
b1 !
b1 )
b1 (
b111 $
b111 '
b1111 #
b1111 &
b1010 "
b1010 %
#8
b1100 !
b1100 )
b1100 (
b101 $
b101 '
b1011 #
b1011 &
b1000 "
b1000 %
#9
b1111 !
b1111 )
b1111 (
b10 $
b10 '
b11 #
b11 &
b1100 "
b1100 %
#10
b0 !
b0 )
b0 (
b111 $
b111 '
b111 #
b111 &
b1010 "
b1010 %
