Ejercicio 2/ROM.v
module memory (input wire [11:0]addres, output wire [7:0]data);

	reg [7:0]mem[0:4095];	

initial begin
	$readmemb("memoria.list",mem);
end

assign data = mem[addres];

endmodule

Ejercicio 2/ROM_tb.v
module testbench();

reg [11:0]addres;
wire [7:0]dato;


memory f(addres,dato);


initial begin
	addres = 12'b000000000000;
	#1 $display("Address = %b, data = %b", addres, dato);
	#1 addres = 12'b000000001000;
	#1 $display("Address = %b, data = %b", addres, dato);
	#1 addres = 12'b000001100000;
	#1 $display("Address = %b, data = %b", addres, dato);
	#1 addres = 12'b000000001111;
	#1 $display("Address = %b, data = %b", addres, dato);
	#1 addres = 12'b000000100001;
	#1 $display("Address = %b, data = %b", addres, dato);
	#1 addres = 12'b000000000011;
	#1 $display("Address = %b, data = %b", addres, dato);
	#1 addres = 12'b000000000101;
	#1 $display("Address = %b, data = %b", addres, dato);
	#1 addres = 12'b000001000000;
	#1 $display("Address = %b, data = %b", addres, dato);
	#1 addres = 12'b000000100010;
	#1 $display("Address = %b, data = %b", addres, dato);
	#1 addres = 12'b000001100110;
	#1 $display("Address = %b, data = %b", addres, dato);
end


initial
	#35 $finish;		
initial begin
	$dumpfile("ROM_tb.vcd");
	$dumpvars(0, testbench);
	end
endmodule

Ejercicio 2/ROM_tb.vcd
$date
	Fri Oct 23 16:09:30 2020
$end
$version
	Icarus Verilog
$end
$timescale
	1ps
$end
$scope module testbench $end
$var wire 8 ! dato [7:0] $end
$var reg 12 " addres [11:0] $end
$scope module f $end
$var wire 12 # addres [11:0] $end
$var wire 8 $ data [7:0] $end
$upscope $end
$upscope $end
$enddefinitions $end
#0
$dumpvars
b0 $
b0 #
b0 "
b0 !
$end
#2
b1000 !
b1000 $
b1000 "
b1000 #
#4
b1100000 !
b1100000 $
b1100000 "
b1100000 #
#6
b1111 !
b1111 $
b1111 "
b1111 #
#8
b100001 !
b100001 $
b100001 "
b100001 #
#10
b11 !
b11 $
b11 "
b11 #
#12
b101 !
b101 $
b101 "
b101 #
#14
b1000000 !
b1000000 $
b1000000 "
b1000000 #
#16
b100010 !
b100010 $
b100010 "
b100010 #
#18
b1100110 !
b1100110 $
b1100110 "
b1100110 #
