Ejercicio 1/contador.v
module counter #(parameter N=12)
		(input logic clk, 
		 input logic reset,
		 input logic load,
		 input logic enabled,
		 input [11:0] d,
		 output logic [N-1:0]q);

always@(posedge clk, posedge reset)
	if(reset)
		q<=0;
	else if (load)
		q<=d;
	else if (enabled)
		q<=q+1;

endmodule

Ejercicio 1/contador_tb.v
module testbench();

reg clk = 0;
reg reset = 1;
reg load = 0;
reg enabled = 0;
reg [11:0]data;
output wire[11:0]q;


counter c1(clk, reset, load, enabled, data, q);

initial begin
	#1 reset = 0;
	#5 enabled = 1;
	#5 data = 12'b000000111000;
	#1 load = 1; #1 load = 0; 
	#6 enabled = 0; data = 12'b000100110000;
	#5 enabled = 1;
	#4 load = 1; #4 load = 0;
	
end



always@(*)begin
	#1 clk = ~clk;
end

always@(*)begin
	#1 clk = ~clk;
end


initial
	#100 $finish;		

initial begin
	$dumpfile("contador_tb.vcd");
	$dumpvars(0, testbench);
	end
endmodule

Ejercicio 1/contador_tb.vcd
$date
	Thu Oct 22 17:09:03 2020
$end
$version
	Icarus Verilog
$end
$timescale
	1ps
$end
$scope module testbench $end
$var wire 12 ! q [11:0] $end
$var reg 1 " clk $end
$var reg 12 # data [11:0] $end
$var reg 1 $ enabled $end
$var reg 1 % load $end
$var reg 1 & reset $end
$scope module c1 $end
$var wire 1 " clk $end
$var wire 12 ' d [11:0] $end
$var wire 1 $ enabled $end
$var wire 1 % load $end
$var wire 1 & reset $end
$var reg 12 ( q [11:0] $end
$upscope $end
$upscope $end
$enddefinitions $end
#0
$dumpvars
b0 (
bx '
1&
0%
0$
bx #
0"
b0 !
$end
#1
0"
0&
#2
1"
#3
0"
#4
1"
#5
0"
#6
b1 !
b1 (
1"
1$
#7
0"
#8
b10 !
b10 (
1"
#9
0"
#10
b11 !
b11 (
1"
#11
0"
b111000 #
b111000 '
#12
b111000 !
b111000 (
1"
1%
#13
0"
0%
#14
b111001 !
b111001 (
1"
#15
0"
#16
b111010 !
b111010 (
1"
#17
0"
#18
b111011 !
b111011 (
1"
#19
0"
b100110000 #
b100110000 '
0$
#20
1"
#21
0"
#22
1"
#23
0"
#24
b111100 !
b111100 (
1"
1$
#25
0"
#26
b111101 !
b111101 (
1"
#27
0"
#28
b100110000 !
b100110000 (
1"
1%
#29
0"
#30
1"
#31
0"
#32
b100110001 !
b100110001 (
1"
0%
#33
0"
#34
b100110010 !
b100110010 (
1"
#35
0"
#36
b100110011 !
b100110011 (
1"
#37
0"
#38
b100110100 !
b100110100 (
1"
#39
0"
#40
b100110101 !
b100110101 (
1"
#41
0"
#42
b100110110 !
b100110110 (
1"
#43
0"
#44
b100110111 !
b100110111 (
1"
#45
0"
#46
b100111000 !
b100111000 (
1"
#47
0"
#48
b100111001 !
b100111001 (
1"
#49
0"
#50
b100111010 !
b100111010 (
1"
#51
0"
#52
b100111011 !
b100111011 (
1"
#53
0"
#54
b100111100 !
b100111100 (
1"
#55
0"
#56
b100111101 !
b100111101 (
1"
#57
0"
#58
b100111110 !
b100111110 (
1"
#59
0"
#60
b100111111 !
b100111111 (
1"
#61
0"
#62
b101000000 !
b101000000 (
1"
#63
0"
#64
b101000001 !
b101000001 (
1"
#65
0"
#66
b101000010 !
b101000010 (
1"
#67
0"
#68
b101000011 !
b101000011 (
1"
#69
0"
#70
b101000100 !
b101000100 (
1"
#71
0"
#72
b101000101 !
b101000101 (
1"
#73
0"
#74
b101000110 !
b101000110 (
1"
#75
0"
#76
b101000111 !
b101000111 (
1"
#77
0"
#78
b101001000 !
b101001000 (
1"
#79
0"
#80
b101001001 !
b101001001 (
1"
#81
0"
#82
b101001010 !
b101001010 (
1"
#83
0"
#84
b101001011 !
b101001011 (
1"
#85
0"
#86
b101001100 !
b101001100 (
1"
#87
0"
#88
b101001101 !
b101001101 (
1"
#89
0"
#90
b101001110 !
b101001110 (
1"
#91
0"
#92
b101001111 !
b101001111 (
1"
#93
0"
#94
b101010000 !
b101010000 (
1"
#95
0"
#96
b101010001 !
b101010001 (
1"
#97
0"
#98
b101010010 !
b101010010 (
1"
#99
0"
#100
b101010011 !
b101010011 (
1"
