Ejercicio 1/contador.v
module counter #(parameter N=12)
		(input logic clk, 
		 input logic reset,
		 output logic [N-1:0]q);

always@(posedge clk, posedge reset)
	if(reset)
		q<=0;
	else
		q<=q+1;
endmodule

Ejercicio 1/contador_tb.v
module testbench();

reg clk = 0;
reg reset = 1;

output wire[11:0]q;

counter c1(clk, reset, q);
initial
	#1 reset = 0;



always@(*)begin
	#1 clk = ~clk;
end

always@(*)begin
	#1 clk = ~clk;
end


initial
	#100 $finish;		

initial begin
	$dumpfile("contador_tb.vcd");
	$dumpvars(0, testbench);
	end
endmodule

Ejercicio 1/contador_tb.vcd
$date
	Thu Oct 22 15:18:48 2020
$end
$version
	Icarus Verilog
$end
$timescale
	1ps
$end
$scope module testbench $end
$var wire 12 ! q [11:0] $end
$var reg 1 " clk $end
$var reg 1 # reset $end
$scope module c1 $end
$var wire 1 " clk $end
$var wire 1 # reset $end
$var reg 12 $ q [11:0] $end
$upscope $end
$upscope $end
$enddefinitions $end
#0
$dumpvars
b0 $
1#
0"
b0 !
$end
#1
b1 !
b1 $
0"
0#
#2
b10 !
b10 $
1"
#3
0"
#4
b11 !
b11 $
1"
#5
0"
#6
b100 !
b100 $
1"
#7
0"
#8
b101 !
b101 $
1"
#9
0"
#10
b110 !
b110 $
1"
#11
0"
#12
b111 !
b111 $
1"
#13
0"
#14
b1000 !
b1000 $
1"
#15
0"
#16
b1001 !
b1001 $
1"
#17
0"
#18
b1010 !
b1010 $
1"
#19
0"
#20
b1011 !
b1011 $
1"
#21
0"
#22
b1100 !
b1100 $
1"
#23
0"
#24
b1101 !
b1101 $
1"
#25
0"
#26
b1110 !
b1110 $
1"
#27
0"
#28
b1111 !
b1111 $
1"
#29
0"
#30
b10000 !
b10000 $
1"
#31
0"
#32
b10001 !
b10001 $
1"
#33
0"
#34
b10010 !
b10010 $
1"
#35
0"
#36
b10011 !
b10011 $
1"
#37
0"
#38
b10100 !
b10100 $
1"
#39
0"
#40
b10101 !
b10101 $
1"
#41
0"
#42
b10110 !
b10110 $
1"
#43
0"
#44
b10111 !
b10111 $
1"
#45
0"
#46
b11000 !
b11000 $
1"
#47
0"
#48
b11001 !
b11001 $
1"
#49
0"
#50
b11010 !
b11010 $
1"
#51
0"
#52
b11011 !
b11011 $
1"
#53
0"
#54
b11100 !
b11100 $
1"
#55
0"
#56
b11101 !
b11101 $
1"
#57
0"
#58
b11110 !
b11110 $
1"
#59
0"
#60
b11111 !
b11111 $
1"
#61
0"
#62
b100000 !
b100000 $
1"
#63
0"
#64
b100001 !
b100001 $
1"
#65
0"
#66
b100010 !
b100010 $
1"
#67
0"
#68
b100011 !
b100011 $
1"
#69
0"
#70
b100100 !
b100100 $
1"
#71
0"
#72
b100101 !
b100101 $
1"
#73
0"
#74
b100110 !
b100110 $
1"
#75
0"
#76
b100111 !
b100111 $
1"
#77
0"
#78
b101000 !
b101000 $
1"
#79
0"
#80
b101001 !
b101001 $
1"
#81
0"
#82
b101010 !
b101010 $
1"
#83
0"
#84
b101011 !
b101011 $
1"
#85
0"
#86
b101100 !
b101100 $
1"
#87
0"
#88
b101101 !
b101101 $
1"
#89
0"
#90
b101110 !
b101110 $
1"
#91
0"
#92
b101111 !
b101111 $
1"
#93
0"
#94
b110000 !
b110000 $
1"
#95
0"
#96
b110001 !
b110001 $
1"
#97
0"
#98
b110010 !
b110010 $
1"
#99
0"
#100
b110011 !
b110011 $
1"
